prevert/__init__.py
prevert-1.0.2.dist-info/LICENSE
prevert-1.0.2.dist-info/METADATA
prevert-1.0.2.dist-info/WHEEL
prevert-1.0.2.dist-info/top_level.txt
prevert-1.0.2.dist-info/RECORD
