Metadata-Version: 2.1
Name: prevert
Version: 1.0.2
Summary: Iterator for prevert files
Author-email: Peter Rupnik <peter.rupnik@ijs.si>, Nikola Ljubešić <nikola.ljubesic@ijs.si>, Taja Kuzman <taja.kuzman@ijs.si>
License: Apache License
Project-URL: Homepage, https://github.com/macocu/prevert/
Keywords: prevertical,prevert,macocu
Classifier: Programming Language :: Python
Classifier: Programming Language :: Python :: 3
Requires-Python: >=3.7
License-File: LICENSE
Provides-Extra: dev
Requires-Dist: black ; extra == 'dev'
Requires-Dist: isort ; extra == 'dev'
Requires-Dist: pip-tools ; extra == 'dev'
Requires-Dist: pytest ; extra == 'dev'
